pytermcanvas/__init__.py
pytermcanvas/canvas.py
pytermcanvas-1.0.0.dist-info/LICENSE
pytermcanvas-1.0.0.dist-info/METADATA
pytermcanvas-1.0.0.dist-info/WHEEL
pytermcanvas-1.0.0.dist-info/top_level.txt
pytermcanvas-1.0.0.dist-info/RECORD
