Metadata-Version: 2.1
Name: pytermcanvas
Version: 1.0.0
Summary: Minimal terminal canvas
Home-page: https://github.com/LukasDrsman/pytermcanvas
Author: Lukáš Dršman
Author-email: lukaskodr@gmail.com
License: UNKNOWN
Platform: UNKNOWN
Classifier: Programming Language :: Python :: 3
Classifier: License :: Public Domain
Classifier: Operating System :: OS Independent
Requires-Python: >=3.7
